AUTHORS
LICENSE
MANIFEST.in
README.rst
setup.py
django_rest_auth.egg-info/PKG-INFO
django_rest_auth.egg-info/SOURCES.txt
django_rest_auth.egg-info/dependency_links.txt
django_rest_auth.egg-info/not-zip-safe
django_rest_auth.egg-info/requires.txt
django_rest_auth.egg-info/top_level.txt
rest_auth/__init__.py
rest_auth/admin.py
rest_auth/app_settings.py
rest_auth/django_test_urls.py
rest_auth/models.py
rest_auth/serializers.py
rest_auth/test_urls.py
rest_auth/tests.py
rest_auth/urls.py
rest_auth/utils.py
rest_auth/views.py
rest_auth/registration/__init__.py
rest_auth/registration/serializers.py
rest_auth/registration/urls.py
rest_auth/registration/views.py